three_commas_websocket_assist/__init__.py
three_commas_websocket_assist/main.py
three_commas_websocket_assist-0.2.1.dist-info/LICENSE
three_commas_websocket_assist-0.2.1.dist-info/METADATA
three_commas_websocket_assist-0.2.1.dist-info/WHEEL
three_commas_websocket_assist-0.2.1.dist-info/top_level.txt
three_commas_websocket_assist-0.2.1.dist-info/RECORD
