Metadata-Version: 2.1
Name: three-commas-websocket-assist
Version: 0.2.1
Summary: 3commas websocket stream assist
Home-page: https://github.com/SaintPepsi/three-commas-websocket-assist
Author: Ron Klinkien & Ian Hogers
Author-email: info@ianhogers.com
License: UNKNOWN
Keywords: python,3commas,api,crypto,cryptocurrency,three commas,bitcoin,trading,btc,eth,websocket
Platform: UNKNOWN
Classifier: Programming Language :: Python :: 3
Classifier: Programming Language :: Python :: 3.8
Classifier: Operating System :: Unix
Classifier: Operating System :: MacOS :: MacOS X
Classifier: Operating System :: Microsoft :: Windows
Requires-Python: >=3.8
License-File: LICENSE
Requires-Dist: rel (==0.4.7)
Requires-Dist: websocket-client (==1.3.2)
